pgqueue.py
pgqueue-0.5.dist-info/DESCRIPTION.rst
pgqueue-0.5.dist-info/METADATA
pgqueue-0.5.dist-info/RECORD
pgqueue-0.5.dist-info/WHEEL
pgqueue-0.5.dist-info/metadata.json
pgqueue-0.5.dist-info/top_level.txt
