Metadata-Version: 2.0
Name: pgqueue
Version: 0.5
Summary: Light PgQ Framework - queuing system for PostgreSQL
Home-page: https://github.com/florentx/pgqueue
Author: Florent Xicluna
Author-email: florent.xicluna@gmail.com
License: ISC
Keywords: postgresql pgq queue
Platform: UNKNOWN
Classifier: Development Status :: 4 - Beta
Classifier: Environment :: Console
Classifier: Intended Audience :: Developers
Classifier: License :: OSI Approved :: ISC License (ISCL)
Classifier: Operating System :: OS Independent
Classifier: Programming Language :: Python
Classifier: Programming Language :: Python :: 2.6
Classifier: Programming Language :: Python :: 2.7
Classifier: Programming Language :: Python :: 3
Classifier: Topic :: Database
Classifier: Topic :: Software Development :: Libraries :: Python Modules
Requires-Dist: psycopg2
